Metadata-Version: 1.0
Name: cutebb
Version: 0.0.1
Summary: for my cute baby
Home-page: https://waitforaday.site
Author: IcedOtaku
Author-email: i@waitforaday.site
License: UNKNOWN
Platform: UNKNOWN
